alu.v
module alu(A, B, op, alt, result);
    parameter WIDTH = 32;
    parameter FUNCT3_ADD = 3'b000;
    parameter FUNCT3_SUB = 3'b000;
    parameter FUNCT3_SLT = 3'b010;
    parameter FUNCT3_SLTU = 3'b011;
    parameter FUNCT3_AND = 3'b111;
    parameter FUNCT3_OR = 3'b110;
    parameter FUNCT3_XOR = 3'b100;
    parameter FUNCT3_SLL = 3'b001;
    parameter FUNCT3_SRL = 3'b101;
    parameter FUNCT3_SRA = 3'b101;
    
    input [WIDTH-1:0] A, B;
    input [2:0] op;
    input alt;
    output reg [WIDTH-1:0] result;
    wire [WIDTH-1:0] subdiff = A + ~B + 1'b1;
    wire equals = (A == B);
    wire sign = subdiff[31];
    wire [4:0] shamt = B[4:0];
    wire [WIDTH-1:0] sign_extend = A[31] ? ~(32'hffffffff >> shamt) : 32'h00000000;
    wire [WIDTH-1:0] op_add = alt ? subdiff : A + B;
    wire [WIDTH-1:0] op_slt = sign && ~equals;
    wire [WIDTH-1:0] op_sltu = A < B;
    wire [WIDTH-1:0] op_and = A & B;
    wire [WIDTH-1:0] op_or = A | B;
    wire [WIDTH-1:0] op_xor = A ^ B;
    wire [WIDTH-1:0] op_sll = A << shamt;
    wire [WIDTH-1:0] op_srl = alt ? (A >> shamt) | sign_extend : A >> shamt;
//calculate A-B, use result for both add and SLT/SLTU
    always @(*) begin
        case(op)
            FUNCT3_ADD: result = op_add;
            FUNCT3_SLT: result = op_slt;
            FUNCT3_SLTU: result = op_sltu;
            FUNCT3_AND: result = op_and;
            FUNCT3_OR: result = op_or;
            FUNCT3_XOR: result = op_xor;
            FUNCT3_SLL: result = op_sll;
            FUNCT3_SRL: result = op_srl;
            default: result = 32'hdeadbeef;
        endcase
    end
endmodule

alu_tb.v
module alu_tb;
    parameter WIDTH = 32;
    parameter FUNCT3_ADD = 3'b000;
    parameter FUNCT3_SUB = 3'b000;
    parameter FUNCT3_SLT = 3'b010;
    parameter FUNCT3_SLTU = 3'b011;
    parameter FUNCT3_AND = 3'b111;
    parameter FUNCT3_OR = 3'b110;
    parameter FUNCT3_XOR = 3'b100;
    parameter FUNCT3_SLL = 3'b001;
    parameter FUNCT3_SRL = 3'b101;
    parameter FUNCT3_SRA = 3'b101;
    
    reg RST = 0;
    initial begin
        #3 RST = 1;
        #5 RST = 0;
    end

    reg CLK = 0;
    always #5 CLK = !CLK;

    initial begin
        $dumpfile("alu_tb.vcd");
        $dumpvars(0, alu_tb);
    end

    reg [WIDTH-1:0] A;
    reg [WIDTH-1:0] B;
    reg [2:0] op;
    reg alt;
    
    wire [WIDTH-1:0] result;
     
    alu uut(A, B, op, alt, result);
    
    initial begin
        // initial code
        A = 2;
        B = 1;
        op = FUNCT3_ADD;
        alt = 0;
        #10;
        A = 2;
        B = 1;
        op = FUNCT3_ADD;
        alt = 1;
        #10;
        A = 1;
        B = 0;
        op = FUNCT3_SLT;
        alt = 0;
        #10;
        A = 0;
        B = 1;
        op = FUNCT3_SLT;
        alt = 0;
        #10;
        A = 32'hffffffff;
        B = 32'haaaaaaaa;
        op = FUNCT3_AND;
        alt = 0;
        #10;
        A = 32'haaaa0000;
        B = 32'h55550000;
        op = FUNCT3_OR;
        alt = 0;
        #10;
        A = 32'haaaaff00;
        B = 32'h5555ff00;
        op = FUNCT3_XOR;
        alt = 0;
        #10;
        A = 32'hffffffff;
        B = 12;
        op = FUNCT3_SLL;
        alt = 0;
        #10;
        A = 32'hffffffff;
        B = 12;
        op = FUNCT3_SRL;
        alt = 0;
        #10;
        $finish;
    end
    
    initial
        $monitor("At time %t, A = %0d, B = %0d, op = %0d, alt = %0d, result = %0d", $time, A, B, op, alt, result);
    
endmodule // alu_tb

alu_tb.vcd
$date
	Tue Oct 18 23:58:08 2022
$end
$version
	Icarus Verilog
$end
$timescale
	1s
$end
$scope module alu_tb $end
$var wire 32 ! result [31:0] $end
$var reg 32 " A [31:0] $end
$var reg 32 # B [31:0] $end
$var reg 1 $ CLK $end
$var reg 1 % RST $end
$var reg 1 & alt $end
$var reg 3 ' op [2:0] $end
$scope module uut $end
$var wire 32 ( A [31:0] $end
$var wire 32 ) B [31:0] $end
$var wire 1 & alt $end
$var wire 3 * op [2:0] $end
$var reg 32 + result [31:0] $end
$upscope $end
$upscope $end
$enddefinitions $end
#0
$dumpvars
b11 +
b0 *
b1 )
b10 (
b0 '
0&
0%
0$
b1 #
b10 "
b11 !
$end
#3
1%
#5
1$
#8
0%
#10
b1 !
b1 +
0$
1&
#15
1$
#20
b0 !
b0 +
0$
0&
b10 '
b10 *
b0 #
b0 )
b1 "
b1 (
#25
1$
#30
b1 !
b1 +
0$
b1 #
b1 )
b0 "
b0 (
#35
1$
#40
b10101010101010101010101010101010 !
b10101010101010101010101010101010 +
0$
b111 '
b111 *
b10101010101010101010101010101010 #
b10101010101010101010101010101010 )
b11111111111111111111111111111111 "
b11111111111111111111111111111111 (
#45
1$
#50
b11111111111111110000000000000000 !
b11111111111111110000000000000000 +
0$
b110 '
b110 *
b1010101010101010000000000000000 #
b1010101010101010000000000000000 )
b10101010101010100000000000000000 "
b10101010101010100000000000000000 (
#55
1$
#60
0$
b100 '
b100 *
b1010101010101011111111100000000 #
b1010101010101011111111100000000 )
b10101010101010101111111100000000 "
b10101010101010101111111100000000 (
#65
1$
#70
b11111111111111111111000000000000 !
b11111111111111111111000000000000 +
0$
b1 '
b1 *
b1100 #
b1100 )
b11111111111111111111111111111111 "
b11111111111111111111111111111111 (
#75
1$
#80
b11111111111111111111 !
b11111111111111111111 +
0$
b101 '
b101 *
