dcache.v
module dcache(address, data_in, read, write, data_out, CLK, RST);
    parameter WIDTH = 32;
    reg [WIDTH-1:0] dcache [7:0];
    
    input wire [WIDTH-1:0] address, data_in;
    input wire read, write;
    output wire [WIDTH-1:0] data_out;
    input CLK, RST;
    
    wire [2:0] index = address[4:2];
    
    //always do this no matter what (read always active basically)
    assign data_out = dcache[index];
    
    always @ (posedge CLK or posedge RST) begin
    	if (RST == 1) begin
    	    dcache[0] <= 32'h00000000;
    	    dcache[1] <= 32'h00000001;
    	    dcache[2] <= 32'h00000002;
    	    dcache[3] <= 32'h00000003;
    	    dcache[4] <= 32'h00000004;
    	    dcache[5] <= 32'h00000005;
    	    dcache[6] <= 32'h00000006;
    	    dcache[7] <= 32'h00000007;
    	end else if (write == 1) begin
    	    dcache[index] <= data_in;
    	// update value
    	end
    end

    initial begin
        $dumpfile("main_tb.vcd");
        $dumpvars(0, dcache[0]);
        $dumpvars(0, dcache[1]);
        $dumpvars(0, dcache[2]);
        $dumpvars(0, dcache[3]);
        $dumpvars(0, dcache[4]);
        $dumpvars(0, dcache[5]);
        $dumpvars(0, dcache[6]);
        $dumpvars(0, dcache[7]);
    end

endmodule

dcache_tb.v
module dcache_tb;
    parameter WIDTH = 32;

    reg RST = 0;
    initial begin
        #3 RST = 1;
        #5 RST = 0;
    end

    reg CLK = 0;
    always #5 CLK = !CLK;

    initial begin
        $dumpfile("dcache_tb.vcd");
        $dumpvars(0, dcache_tb);
    end

    reg [WIDTH-1:0] address;
    reg [WIDTH-1:0] data_in;
    reg read;
    reg write;
    
    wire [WIDTH-1:0] data_out;
     
    dcache dmem(address, data_in, read, write, data_out, CLK, RST);
    
    initial begin
        // initial code
        address = 0;
        data_in = 0;
        read = 0;
        write = 0;
        #10;
        address = 4;
        data_in = 32'h00000011;
        read = 0;
        write = 1;
        #10;
        address = 4;
        data_in = 32'h00000011;
        read = 1;
        write = 0;
        #10;
        address = 8;
        data_in = 32'h00000012;
        read = 0;
        write = 1;
        #10;
        address = 8;
        data_in = 32'h00000022;
        read = 0;
        write = 1;
        #10;
        address = 8;
        data_in = 32'h00000000;
        read = 1;
        write = 0;
        #10;
        address = 12;
        data_in = 32'h00000011;
        read = 1;
        write = 0;
        #10;
        address = 16;
        data_in = 32'h00000011;
        read = 1;
        write = 0;
        #10;
        $finish;
    end
    
    initial
        $monitor("At time %t, address = %0d, data_in = %0d, read = %0d, write = %0d, data_out = %0d", $time, address, data_in, read, write, data_out);
    
endmodule // dcache_tb

dcache_tb.vcd
$date
	Tue Nov  1 00:51:31 2022
$end
$version
	Icarus Verilog
$end
$timescale
	1s
$end
$scope module dcache_tb $end
$var wire 32 ! data_out [31:0] $end
$var reg 1 " CLK $end
$var reg 1 # RST $end
$var reg 32 $ address [31:0] $end
$var reg 32 % data_in [31:0] $end
$var reg 1 & read $end
$var reg 1 ' write $end
$scope module dmem $end
$var wire 1 " CLK $end
$var wire 1 # RST $end
$var wire 32 ( address [31:0] $end
$var wire 32 ) data_in [31:0] $end
$var wire 32 * data_out [31:0] $end
$var wire 1 & read $end
$var wire 1 ' write $end
$var wire 3 + index [2:0] $end
$upscope $end
$upscope $end
$enddefinitions $end
#0
$dumpvars
b0 +
bx *
b0 )
b0 (
0'
0&
b0 %
b0 $
0#
0"
bx !
$end
#3
b0 !
b0 *
1#
#5
1"
#8
0#
#10
b1 !
b1 *
b1 +
0"
1'
b10001 %
b10001 )
b100 $
b100 (
#15
b10001 !
b10001 *
1"
#20
0"
0'
1&
#25
1"
#30
b10 !
b10 *
b10 +
0"
1'
0&
b10010 %
b10010 )
b1000 $
b1000 (
#35
b10010 !
b10010 *
1"
#40
0"
b100010 %
b100010 )
#45
b100010 !
b100010 *
1"
#50
0"
0'
1&
b0 %
b0 )
#55
1"
#60
b11 !
b11 *
b11 +
0"
b10001 %
b10001 )
b1100 $
b1100 (
#65
1"
#70
b100 !
b100 *
b100 +
0"
b10000 $
b10000 (
